README.md
setup.py
django_payments_razorpay/__init__.py
django_payments_razorpay/forms.py
django_payments_razorpay/widgets.py
django_payments_razorpay.egg-info/PKG-INFO
django_payments_razorpay.egg-info/SOURCES.txt
django_payments_razorpay.egg-info/dependency_links.txt
django_payments_razorpay.egg-info/not-zip-safe
django_payments_razorpay.egg-info/requires.txt
django_payments_razorpay.egg-info/top_level.txt